iparse/__init__.py
iparse/_parse.py
tests/__init__.py
tests/test_iparser.py
tests/test_json_parser.py
tests/test_linkedin.py
tests/test_xkcd01.py
iparse-0.0.6.4.dist-info/LICENSE
iparse-0.0.6.4.dist-info/METADATA
iparse-0.0.6.4.dist-info/WHEEL
iparse-0.0.6.4.dist-info/top_level.txt
iparse-0.0.6.4.dist-info/RECORD
